<annotation>
	<filename>2011_003021.jpg</filename>
	<folder>VOC2012</folder>
	<object>
		<name>person</name>
		<bndbox>
			<xmax>290</xmax>
			<xmin>199</xmin>
			<ymax>343</ymax>
			<ymin>141</ymin>
		</bndbox>
		<difficult>0</difficult>
		<occluded>0</occluded>
		<pose>Frontal</pose>
		<truncated>0</truncated>
		<part>
			<name>head</name>
			<bndbox>
				<xmin>228</xmin>
				<ymin>141</ymin>
				<xmax>262</xmax>
				<ymax>181</ymax>
			</bndbox>
		</part>
		<part>
			<name>hand</name>
			<bndbox>
				<xmin>230</xmin>
				<ymin>242</ymin>
				<xmax>239</xmax>
				<ymax>265</ymax>
			</bndbox>
		</part>
		<part>
			<name>hand</name>
			<bndbox>
				<xmin>234</xmin>
				<ymin>242</ymin>
				<xmax>250</xmax>
				<ymax>269</ymax>
			</bndbox>
		</part>
		<part>
			<name>foot</name>
			<bndbox>
				<xmin>210</xmin>
				<ymin>333</ymin>
				<xmax>228</xmax>
				<ymax>342</ymax>
			</bndbox>
		</part>
		<part>
			<name>foot</name>
			<bndbox>
				<xmin>263</xmin>
				<ymin>331</ymin>
				<xmax>283</xmax>
				<ymax>340</ymax>
			</bndbox>
		</part>
	</object>
	<segmented>0</segmented>
	<size>
		<depth>3</depth>
		<height>375</height>
		<width>500</width>
	</size>
	<source>
		<annotation>PASCAL VOC2011</annotation>
		<database>The VOC2011 Database</database>
		<image>flickr</image>
	</source>
</annotation>
