<annotation>
	<filename>2011_002520.jpg</filename>
	<folder>VOC2012</folder>
	<object>
		<name>horse</name>
		<bndbox>
			<xmax>353</xmax>
			<xmin>249</xmin>
			<ymax>264</ymax>
			<ymin>17</ymin>
		</bndbox>
		<difficult>0</difficult>
		<occluded>0</occluded>
		<pose>Frontal</pose>
		<truncated>0</truncated>
	</object>
	<object>
		<name>horse</name>
		<bndbox>
			<xmax>250</xmax>
			<xmin>146</xmin>
			<ymax>277</ymax>
			<ymin>18</ymin>
		</bndbox>
		<difficult>0</difficult>
		<occluded>0</occluded>
		<pose>Frontal</pose>
		<truncated>0</truncated>
	</object>
	<object>
		<name>horse</name>
		<bndbox>
			<xmax>133</xmax>
			<xmin>25</xmin>
			<ymax>277</ymax>
			<ymin>27</ymin>
		</bndbox>
		<difficult>0</difficult>
		<occluded>0</occluded>
		<pose>Frontal</pose>
		<truncated>0</truncated>
	</object>
	<object>
		<name>horse</name>
		<bndbox>
			<xmax>466</xmax>
			<xmin>342</xmin>
			<ymax>263</ymax>
			<ymin>22</ymin>
		</bndbox>
		<difficult>0</difficult>
		<occluded>1</occluded>
		<pose>Frontal</pose>
		<truncated>0</truncated>
	</object>
	<segmented>0</segmented>
	<size>
		<depth>3</depth>
		<height>400</height>
		<width>500</width>
	</size>
	<source>
		<annotation>PASCAL VOC2011</annotation>
		<database>The VOC2011 Database</database>
		<image>flickr</image>
	</source>
</annotation>
