<annotation>
	<filename>2011_001668.jpg</filename>
	<folder>VOC2012</folder>
	<object>
		<name>person</name>
		<bndbox>
			<xmax>162</xmax>
			<xmin>104</xmin>
			<ymax>420</ymax>
			<ymin>274</ymin>
		</bndbox>
		<difficult>0</difficult>
		<occluded>0</occluded>
		<pose>Unspecified</pose>
		<truncated>0</truncated>
		<part>
			<name>foot</name>
			<bndbox>
				<xmin>116</xmin>
				<ymin>404</ymin>
				<xmax>129</xmax>
				<ymax>420</ymax>
			</bndbox>
		</part>
		<part>
			<name>foot</name>
			<bndbox>
				<xmin>133</xmin>
				<ymin>402</ymin>
				<xmax>148</xmax>
				<ymax>412</ymax>
			</bndbox>
		</part>
		<part>
			<name>hand</name>
			<bndbox>
				<xmin>151</xmin>
				<ymin>341</ymin>
				<xmax>161</xmax>
				<ymax>357</ymax>
			</bndbox>
		</part>
		<part>
			<name>hand</name>
			<bndbox>
				<xmin>105</xmin>
				<ymin>336</ymin>
				<xmax>113</xmax>
				<ymax>348</ymax>
			</bndbox>
		</part>
		<part>
			<name>head</name>
			<bndbox>
				<xmin>123</xmin>
				<ymin>274</ymin>
				<xmax>139</xmax>
				<ymax>297</ymax>
			</bndbox>
		</part>
	</object>
	<segmented>0</segmented>
	<size>
		<depth>3</depth>
		<height>442</height>
		<width>500</width>
	</size>
	<source>
		<annotation>PASCAL VOC2011</annotation>
		<database>The VOC2011 Database</database>
		<image>flickr</image>
	</source>
</annotation>
