<annotation>
	<filename>2011_002045.jpg</filename>
	<folder>VOC2012</folder>
	<object>
		<name>pottedplant</name>
		<bndbox>
			<xmax>484</xmax>
			<xmin>420</xmin>
			<ymax>219</ymax>
			<ymin>142</ymin>
		</bndbox>
		<difficult>0</difficult>
		<occluded>1</occluded>
		<pose>Unspecified</pose>
		<truncated>0</truncated>
	</object>
	<object>
		<name>pottedplant</name>
		<bndbox>
			<xmax>29</xmax>
			<xmin>1</xmin>
			<ymax>341</ymax>
			<ymin>262</ymin>
		</bndbox>
		<difficult>1</difficult>
		<occluded>0</occluded>
		<pose>Unspecified</pose>
		<truncated>1</truncated>
	</object>
	<object>
		<name>pottedplant</name>
		<bndbox>
			<xmax>16</xmax>
			<xmin>1</xmin>
			<ymax>200</ymax>
			<ymin>125</ymin>
		</bndbox>
		<difficult>1</difficult>
		<occluded>0</occluded>
		<pose>Unspecified</pose>
		<truncated>1</truncated>
	</object>
	<object>
		<name>person</name>
		<bndbox>
			<xmax>134</xmax>
			<xmin>54</xmin>
			<ymax>375</ymax>
			<ymin>249</ymin>
		</bndbox>
		<difficult>0</difficult>
		<occluded>0</occluded>
		<pose>Frontal</pose>
		<truncated>1</truncated>
	</object>
	<object>
		<name>person</name>
		<bndbox>
			<xmax>190</xmax>
			<xmin>119</xmin>
			<ymax>373</ymax>
			<ymin>212</ymin>
		</bndbox>
		<difficult>0</difficult>
		<occluded>1</occluded>
		<pose>Frontal</pose>
		<truncated>1</truncated>
	</object>
	<object>
		<name>person</name>
		<bndbox>
			<xmax>280</xmax>
			<xmin>197</xmin>
			<ymax>375</ymax>
			<ymin>208</ymin>
		</bndbox>
		<difficult>0</difficult>
		<occluded>1</occluded>
		<pose>Frontal</pose>
		<truncated>0</truncated>
	</object>
	<object>
		<name>person</name>
		<bndbox>
			<xmax>326</xmax>
			<xmin>258</xmin>
			<ymax>375</ymax>
			<ymin>237</ymin>
		</bndbox>
		<difficult>0</difficult>
		<occluded>0</occluded>
		<pose>Frontal</pose>
		<truncated>1</truncated>
	</object>
	<object>
		<name>person</name>
		<bndbox>
			<xmax>416</xmax>
			<xmin>303</xmin>
			<ymax>375</ymax>
			<ymin>219</ymin>
		</bndbox>
		<difficult>0</difficult>
		<occluded>1</occluded>
		<pose>Frontal</pose>
		<truncated>1</truncated>
	</object>
	<object>
		<name>person</name>
		<bndbox>
			<xmax>150</xmax>
			<xmin>79</xmin>
			<ymax>265</ymax>
			<ymin>134</ymin>
		</bndbox>
		<difficult>0</difficult>
		<occluded>1</occluded>
		<pose>Right</pose>
		<truncated>1</truncated>
	</object>
	<object>
		<name>person</name>
		<bndbox>
			<xmax>214</xmax>
			<xmin>152</xmin>
			<ymax>239</ymax>
			<ymin>133</ymin>
		</bndbox>
		<difficult>0</difficult>
		<occluded>1</occluded>
		<pose>Frontal</pose>
		<truncated>1</truncated>
	</object>
	<object>
		<name>person</name>
		<bndbox>
			<xmax>257</xmax>
			<xmin>210</xmin>
			<ymax>241</ymax>
			<ymin>136</ymin>
		</bndbox>
		<difficult>0</difficult>
		<occluded>1</occluded>
		<pose>Frontal</pose>
		<truncated>1</truncated>
	</object>
	<object>
		<name>person</name>
		<bndbox>
			<xmax>304</xmax>
			<xmin>257</xmin>
			<ymax>238</ymax>
			<ymin>138</ymin>
		</bndbox>
		<difficult>0</difficult>
		<occluded>1</occluded>
		<pose>Frontal</pose>
		<truncated>1</truncated>
	</object>
	<object>
		<name>person</name>
		<bndbox>
			<xmax>351</xmax>
			<xmin>293</xmin>
			<ymax>241</ymax>
			<ymin>133</ymin>
		</bndbox>
		<difficult>0</difficult>
		<occluded>1</occluded>
		<pose>Frontal</pose>
		<truncated>1</truncated>
	</object>
	<object>
		<name>person</name>
		<bndbox>
			<xmax>394</xmax>
			<xmin>334</xmin>
			<ymax>261</ymax>
			<ymin>131</ymin>
		</bndbox>
		<difficult>0</difficult>
		<occluded>1</occluded>
		<pose>Frontal</pose>
		<truncated>1</truncated>
	</object>
	<object>
		<name>sofa</name>
		<bndbox>
			<xmax>392</xmax>
			<xmin>193</xmin>
			<ymax>302</ymax>
			<ymin>157</ymin>
		</bndbox>
		<difficult>1</difficult>
		<occluded>1</occluded>
		<pose>Frontal</pose>
		<truncated>1</truncated>
	</object>
	<object>
		<name>chair</name>
		<bndbox>
			<xmax>91</xmax>
			<xmin>16</xmin>
			<ymax>351</ymax>
			<ymin>166</ymin>
		</bndbox>
		<difficult>0</difficult>
		<occluded>1</occluded>
		<pose>Unspecified</pose>
		<truncated>1</truncated>
	</object>
	<object>
		<name>chair</name>
		<bndbox>
			<xmax>500</xmax>
			<xmin>402</xmin>
			<ymax>352</ymax>
			<ymin>173</ymin>
		</bndbox>
		<difficult>1</difficult>
		<occluded>1</occluded>
		<pose>Left</pose>
		<truncated>1</truncated>
	</object>
	<segmented>0</segmented>
	<size>
		<depth>3</depth>
		<height>375</height>
		<width>500</width>
	</size>
	<source>
		<annotation>PASCAL VOC2011</annotation>
		<database>The VOC2011 Database</database>
		<image>flickr</image>
	</source>
</annotation>
